{"openapi":"3.0.0","description":"bla bla bla","info":{"version":"0.0.0","title":"EAPI"},"paths":{"/":{"get":{"summary":"Make a ping request","responses":{"200":{"description":"Ping response","content":{"application/json":{"schema":{"type":"object","properties":{"greetings":{"type":"string"},"date":{"type":"string"},"url":{"type":"string"},"headers":{"type":"object"}}}}}}},"parameters":[{"name":"token","in":"header","description":"The token identifier string","required":true,"schema":{"type":"string"}}]}},"/:id":{"get":{"parameters":[{}]}},"/new":{"post":{"requestBody":{}}},"/update/:id":{"put":{"requestBody":{},"parameters":[{}]}},"/delete/:id":{"delete":{"parameters":[{}]}}},"components":{"schemas":{}}}